ovmfkeyenroll/SecureBootEnable.bin
ovmfkeyenroll/__init__.py
ovmfkeyenroll/secure_boot.py
ovmfkeyenroll/var_enroll.py
ovmfkeyenroll-1.2.1.dist-info/METADATA
ovmfkeyenroll-1.2.1.dist-info/WHEEL
ovmfkeyenroll-1.2.1.dist-info/entry_points.txt
ovmfkeyenroll-1.2.1.dist-info/licenses/LICENSE
ovmfkeyenroll-1.2.1.dist-info/RECORD
