Metadata-Version: 2.1
Name: ovmfkeyenroll
Version: 1.2.1
Summary: OVMF PK, KEK and DB Keys and Variables Enrolling
Project-URL: Homepage, https://github.com/intel/tdx-tools/tree/main/utils/ovmfkeyenroll
Project-URL: Bug Tracker, https://github.com/intel/tdx-tools/issues
Author-email: "Xu, Min" <min.m.xu@intel.com>, "Feng, Jialei" <jialei.feng@intel.com>
License-File: LICENSE
Classifier: Development Status :: 3 - Alpha
Classifier: License :: OSI Approved :: Apache Software License
Classifier: Operating System :: POSIX :: Linux
Classifier: Programming Language :: Python :: 3
Classifier: Topic :: Software Development :: Testing
Classifier: Topic :: System :: Boot
Requires-Python: >=3.6.8
